progressbars/__init__.py
progressbars/progressbar.py
progressbars/widgets.py
progressbars-1.1.10.dist-info/LICENSE
progressbars-1.1.10.dist-info/METADATA
progressbars-1.1.10.dist-info/WHEEL
progressbars-1.1.10.dist-info/top_level.txt
progressbars-1.1.10.dist-info/RECORD
