Metadata-Version: 2.1
Name: progressbars
Version: 1.1.10
Summary: A python package to display progress of loops to the user
Home-page: https://github.com/Matthias1590/ProgressBars
Author: Matthias Wijnsma
Author-email: matthiasx95@gmail.com
License: MIT
Platform: UNKNOWN
License-File: LICENSE
